gamestorm/__init__.py
gamestorm/constants.py
gamestorm/gamestorm.py
gamestorm/symbol_group.py
gamestorm/tile.py
gamestorm/resources/background/1.png
gamestorm/resources/background/10.png
gamestorm/resources/background/100.png
gamestorm/resources/background/101.png
gamestorm/resources/background/102.png
gamestorm/resources/background/103.png
gamestorm/resources/background/104.png
gamestorm/resources/background/105.png
gamestorm/resources/background/106.png
gamestorm/resources/background/107.png
gamestorm/resources/background/108.png
gamestorm/resources/background/109.png
gamestorm/resources/background/11.png
gamestorm/resources/background/110.png
gamestorm/resources/background/111.png
gamestorm/resources/background/112.png
gamestorm/resources/background/113.png
gamestorm/resources/background/114.png
gamestorm/resources/background/115.png
gamestorm/resources/background/116.png
gamestorm/resources/background/117.png
gamestorm/resources/background/118.png
gamestorm/resources/background/119.png
gamestorm/resources/background/12.png
gamestorm/resources/background/120.png
gamestorm/resources/background/121.png
gamestorm/resources/background/122.png
gamestorm/resources/background/123.png
gamestorm/resources/background/124.png
gamestorm/resources/background/125.png
gamestorm/resources/background/126.png
gamestorm/resources/background/127.png
gamestorm/resources/background/128.png
gamestorm/resources/background/129.png
gamestorm/resources/background/13.png
gamestorm/resources/background/130.png
gamestorm/resources/background/131.png
gamestorm/resources/background/132.png
gamestorm/resources/background/133.png
gamestorm/resources/background/134.png
gamestorm/resources/background/135.png
gamestorm/resources/background/136.png
gamestorm/resources/background/137.png
gamestorm/resources/background/138.png
gamestorm/resources/background/139.png
gamestorm/resources/background/14.png
gamestorm/resources/background/140.png
gamestorm/resources/background/141.png
gamestorm-1.0.0.dist-info/METADATA
gamestorm-1.0.0.dist-info/WHEEL
gamestorm-1.0.0.dist-info/top_level.txt
gamestorm-1.0.0.dist-info/RECORD
