Metadata-Version: 2.1
Name: gamestorm
Version: 1.0.0
Summary: A minimal, batteries included, 2D game engine using grid-based graphics.
Home-page: https://github.com/agsilvio/gamestorm-library
Author: Silvio Marco Costantini
Author-email: agsilvio@protonmail.com
License: UNKNOWN
Platform: UNKNOWN
Classifier: Programming Language :: Python :: 3
Classifier: License :: OSI Approved :: MIT License
Classifier: Operating System :: OS Independent
Requires-Dist: pygame
Requires-Dist: unittest2
Requires-Dist: nose2
